MANIFEST.in
README.rst
distribute_setup.py
setup.py
dpnewman.egg-info/PKG-INFO
dpnewman.egg-info/SOURCES.txt
dpnewman.egg-info/dependency_links.txt
dpnewman.egg-info/requires.txt
dpnewman.egg-info/top_level.txt
src/dpnewman.c
src/dpnewman.pyx
test/test_dpnewman.py