Metadata-Version: 1.0
Name: dpnewman
Version: 0.01
Summary: DP-Newman Graph Generative Model
Home-page: UNKNOWN
Author: UNKNOWN
Author-email: UNKNOWN
License: UNKNOWN
Platform: UNKNOWN
